docker_compose_builder/__init__.py
docker_compose_builder/docker-template.yml
docker_compose_builder/main.py
docker_compose_builder-0.2.dist-info/LICENSE
docker_compose_builder-0.2.dist-info/METADATA
docker_compose_builder-0.2.dist-info/WHEEL
docker_compose_builder-0.2.dist-info/entry_points.txt
docker_compose_builder-0.2.dist-info/top_level.txt
docker_compose_builder-0.2.dist-info/RECORD
