Metadata-Version: 2.1
Name: docker-compose-builder
Version: 0.2
Summary: "CLI tool to build Docker Compose files from templates"
Home-page: https://github.com/yash2002vardhan
Author: Yashvardhan Goel
Author-email: yashvardhan090202@gmail.com
Classifier: Development Status :: 3 - Alpha
Classifier: License :: OSI Approved :: MIT License
Classifier: Programming Language :: Python :: 3.10
Classifier: Operating System :: OS Independent
Requires-Python: >=3.10
License-File: LICENSE
Requires-Dist: typer
Requires-Dist: ruamel.yaml
Requires-Dist: setuptools
